atri_core/AtriComponent.py
atri_core/AtriStyles.py
atri_core/__init__.py
atri_core/send_ipc_msg.py
atri_core-1.0.0a26.dist-info/METADATA
atri_core-1.0.0a26.dist-info/WHEEL
atri_core-1.0.0a26.dist-info/top_level.txt
atri_core-1.0.0a26.dist-info/RECORD
