Metadata-Version: 2.1
Name: atri-core
Version: 1.0.0a26
Summary: The best tools to build better and fast apps
Home-page: https://atrilabs.com
Author: Atri Labs
Author-email: shyam.swaroop@atrilabs.com
License: GPLv3
Project-URL: Source, https://github.com/cruxcode/atrilabs-engine.git
Requires-Python: >=3.7
